{
  "_class": "shapePath",
  "booleanOperation": -1,
  "do_objectID": "511BF911-7B3D-4573-81BD-B0BAD805D907",
  "edited": true,
  "exportOptions": {
    "_class": "exportOptions",
    "exportFormats": [
    ],
    "includedLayerIds": [
    ],
    "layerOptions": 0,
    "shouldTrim": false
  },
  "frame": {
    "_class": "rect",
    "constrainProportions": false,
    "height": 8.800000000000011,
    "width": 20.89999999999998,
    "x": 19.30000000000098,
    "y": 42.29999999999984
  },
  "isFlippedHorizontal": false,
  "isFlippedVertical": false,
  "isLocked": false,
  "isVisible": true,
  "layerListExpandedType": 0,
  "name": "Path",
  "nameIsFixed": false,
  "path": {
    "_class": "path",
    "isClosed": true,
    "pointRadiusBehaviour": 0,
    "points": [
      {
        "_class": "curvePoint",
        "cornerRadius": 0,
        "curveFrom": "{0, 0.8409090909090905}",
        "curveMode": 1,
        "curveTo": "{0, 0.8409090909090905}",
        "hasCurveFrom": false,
        "hasCurveTo": false,
        "point": "{0, 0.8409090909090905}"
      },
      {
        "_class": "curvePoint",
        "cornerRadius": 0,
        "curveFrom": "{0.047846889952153165, 0}",
        "curveMode": 1,
        "curveTo": "{0.047846889952153165, 0}",
        "hasCurveFrom": false,
        "hasCurveTo": false,
        "point": "{0.047846889952153165, 0}"
      },
      {
        "_class": "curvePoint",
        "cornerRadius": 0,
        "curveFrom": "{1, 0.22727272727272699}",
        "curveMode": 1,
        "curveTo": "{1, 0.22727272727272699}",
        "hasCurveFrom": false,
        "hasCurveTo": false,
        "point": "{1, 0.22727272727272699}"
      },
      {
        "_class": "curvePoint",
        "cornerRadius": 0,
        "curveFrom": "{0.98086124401913988, 1}",
        "curveMode": 1,
        "curveTo": "{0.98086124401913988, 1}",
        "hasCurveFrom": false,
        "hasCurveTo": false,
        "point": "{0.98086124401913988, 1}"
      },
      {
        "_class": "curvePoint",
        "cornerRadius": 0,
        "curveFrom": "{0, 0.8409090909090905}",
        "curveMode": 1,
        "curveTo": "{0, 0.8409090909090905}",
        "hasCurveFrom": false,
        "hasCurveTo": false,
        "point": "{0, 0.8409090909090905}"
      }
    ]
  },
  "resizingConstraint": 63,
  "resizingType": 0,
  "rotation": 0,
  "shouldBreakMaskChain": false
}