{
  "_class": "shapePath",
  "booleanOperation": -1,
  "do_objectID": "A10ADCD5-09F7-4B32-8670-65F566F0CC0E",
  "edited": true,
  "exportOptions": {
    "_class": "exportOptions",
    "do_objectID": "C7BC70FD-4176-4814-ACEF-AAA4A75263FC",
    "exportFormats": [
    ],
    "includedLayerIds": [
    ],
    "layerOptions": 0,
    "shouldTrim": false
  },
  "frame": {
    "_class": "rect",
    "constrainProportions": false,
    "do_objectID": "B1C47724-5EAE-406D-AFCB-FB761E53C057",
    "height": 2,
    "width": 752,
    "x": 0,
    "y": 0
  },
  "isClosed": false,
  "isFlippedHorizontal": false,
  "isFlippedVertical": false,
  "isLocked": false,
  "isVisible": true,
  "layerListExpandedType": 0,
  "name": "Path",
  "nameIsFixed": false,
  "pointRadiusBehaviour": 1,
  "points": [
    {
      "_class": "curvePoint",
      "cornerRadius": 0,
      "curveFrom": "{0.0021251865317268616, 0.875}",
      "curveMode": 1,
      "curveTo": "{0.0021251865317268616, 0.875}",
      "hasCurveFrom": false,
      "hasCurveTo": false,
      "point": "{0, 0.5}"
    },
    {
      "_class": "curvePoint",
      "cornerRadius": 0,
      "curveFrom": "{0.0032135015280711611, 1}",
      "curveMode": 1,
      "curveTo": "{0.0032135015280711611, 1}",
      "hasCurveFrom": false,
      "hasCurveTo": false,
      "point": "{1, 0.5}"
    }
  ],
  "resizingConstraint": 63,
  "resizingType": 0,
  "rotation": 0,
  "shouldBreakMaskChain": false,
  "userInfo": {
    "com.animaapp.stc-sketch-plugin": {
      "kModelPropertiesKey": {
      }
    }
  }
}