{
  "_class": "group",
  "do_objectID": "C5BF9D57-C33F-4D85-81C9-389C3CE969C2",
  "exportOptions": {
    "_class": "exportOptions",
    "exportFormats": [
    ],
    "includedLayerIds": [
    ],
    "layerOptions": 0,
    "shouldTrim": false
  },
  "frame": {
    "_class": "rect",
    "constrainProportions": false,
    "height": 56,
    "width": 238,
    "x": 80,
    "y": 393
  },
  "hasClickThrough": false,
  "isFlippedHorizontal": false,
  "isFlippedVertical": false,
  "isLocked": false,
  "isVisible": true,
  "layerListExpandedType": 2,
  "layers": [
    {
      "class": "shapeGroup",
      "id": "26A0A7AF-9921-495F-A898-4FFAFF018A54"
    },
    {
      "class": "symbolInstance",
      "id": "CAAC2D6D-82A8-414F-8D7E-2316E1341E69"
    },
    {
      "class": "text",
      "id": "1FDB2AFF-9608-47C1-8B8D-8E26BCAC0C32"
    }
  ],
  "name": "Platform-filter",
  "nameIsFixed": true,
  "resizingConstraint": 63,
  "resizingType": 0,
  "rotation": 0,
  "shouldBreakMaskChain": false,
  "style": {
    "_class": "style",
    "endDecorationType": 0,
    "miterLimit": 10,
    "startDecorationType": 0
  },
  "userInfo": {
    "com.animaapp.stc-sketch-plugin": {
      "kModelPropertiesKey": {
      }
    }
  }
}