{
  "_class": "symbolInstance",
  "do_objectID": "53853B3C-9272-4FA3-BBD6-0363BD95428E",
  "exportOptions": {
    "_class": "exportOptions",
    "do_objectID": "1F722A54-886F-4C5F-A8F1-D14C62CDBAC1",
    "exportFormats": [
    ],
    "includedLayerIds": [
    ],
    "layerOptions": 0,
    "shouldTrim": false
  },
  "frame": {
    "_class": "rect",
    "constrainProportions": false,
    "do_objectID": "74D0DA4B-203F-46E6-9226-55B523F196F7",
    "height": 48,
    "width": 92,
    "x": 800,
    "y": 0
  },
  "horizontalSpacing": 0,
  "isFlippedHorizontal": false,
  "isFlippedVertical": false,
  "isLocked": false,
  "isVisible": true,
  "layerListExpandedType": 0,
  "name": "table/data-cell/striped",
  "nameIsFixed": false,
  "overrideValues": [
  ],
  "resizingConstraint": 63,
  "resizingType": 0,
  "rotation": 0,
  "scale": 1,
  "shouldBreakMaskChain": false,
  "style": {
    "_class": "style",
    "do_objectID": "579143BF-937E-42B7-80E5-F3D1DF7A83E9",
    "endDecorationType": 0,
    "miterLimit": 10,
    "startDecorationType": 0
  },
  "symbolID": "AE993D3D-1867-47E3-8905-FE4A996ED031",
  "userInfo": {
    "com.animaapp.stc-sketch-plugin": {
      "kModelPropertiesKey": {
      }
    }
  },
  "verticalSpacing": 0
}