{
  "_class": "shapePath",
  "booleanOperation": -1,
  "do_objectID": "79034726-4FE7-4164-AD0F-A083F95D45F8",
  "edited": true,
  "exportOptions": {
    "_class": "exportOptions",
    "exportFormats": [
    ],
    "includedLayerIds": [
    ],
    "layerOptions": 0,
    "shouldTrim": false
  },
  "frame": {
    "_class": "rect",
    "constrainProportions": false,
    "height": 3,
    "width": 1073,
    "x": 0,
    "y": 0
  },
  "isClosed": false,
  "isFlippedHorizontal": false,
  "isFlippedVertical": false,
  "isLocked": false,
  "isVisible": true,
  "layerListExpandedType": 0,
  "name": "Path",
  "nameIsFixed": false,
  "pointRadiusBehaviour": 1,
  "points": [
    {
      "_class": "curvePoint",
      "cornerRadius": 0,
      "curveFrom": "{0.0033533460129157493, 0.91666666666666652}",
      "curveMode": 1,
      "curveTo": "{0.0033533460129157493, 0.91666666666666652}",
      "hasCurveFrom": false,
      "hasCurveTo": false,
      "point": "{0.0004658739927242561, 0.66666666666662311}"
    },
    {
      "_class": "curvePoint",
      "cornerRadius": 0,
      "curveFrom": "{0.0041160793561132464, 1}",
      "curveMode": 1,
      "curveTo": "{0.0041160793561132464, 1}",
      "hasCurveFrom": false,
      "hasCurveTo": false,
      "point": "{0.99953412544683928, 0.66666666666662311}"
    }
  ],
  "resizingConstraint": 63,
  "resizingType": 0,
  "rotation": 0,
  "shouldBreakMaskChain": false,
  "userInfo": {
    "com.animaapp.stc-sketch-plugin": {
      "kModelPropertiesKey": {
      }
    }
  }
}