{
  "_class": "symbolInstance",
  "do_objectID": "B2CC851F-CB1A-4B48-8860-723EC6049E69",
  "exportOptions": {
    "_class": "exportOptions",
    "do_objectID": "133E4E03-7672-4873-AF1D-3C3915B9266D",
    "exportFormats": [
    ],
    "includedLayerIds": [
    ],
    "layerOptions": 0,
    "shouldTrim": false
  },
  "frame": {
    "_class": "rect",
    "constrainProportions": false,
    "do_objectID": "55100E1B-CA8E-42E5-A319-1E51DC43045E",
    "height": 32,
    "width": 181,
    "x": 82,
    "y": 0
  },
  "horizontalSpacing": 0,
  "isFlippedHorizontal": false,
  "isFlippedVertical": false,
  "isLocked": false,
  "isVisible": true,
  "layerListExpandedType": 0,
  "name": "forms/dropdown_states/normal",
  "nameIsFixed": false,
  "overrideValues": [
    {
      "_class": "overrideValue",
      "do_objectID": "C5500CD5-9BD6-4FAE-B7AD-9527C915C0AC",
      "overrideName": "D8D72A8F-0F02-4B4A-B865-5F3C0072CDD0_stringValue",
      "value": "Species"
    }
  ],
  "overrides": {
    "D8D72A8F-0F02-4B4A-B865-5F3C0072CDD0": "Species"
  },
  "resizingConstraint": 63,
  "resizingType": 0,
  "rotation": 0,
  "scale": 1,
  "shouldBreakMaskChain": false,
  "style": {
    "_class": "style",
    "do_objectID": "8EE941E7-EF36-4806-9D8C-9E8E5979E55D",
    "endDecorationType": 0,
    "miterLimit": 10,
    "startDecorationType": 0
  },
  "symbolID": "76D345EC-A925-4AD6-9D9F-08BE240161EF",
  "userInfo": {
    "com.animaapp.stc-sketch-plugin": {
      "kModelPropertiesKey": {
      }
    }
  },
  "verticalSpacing": 0
}