{
  "_class": "group",
  "do_objectID": "A01EFD79-B532-4176-A65C-51CCC151CBE3",
  "exportOptions": {
    "_class": "exportOptions",
    "exportFormats": [
    ],
    "includedLayerIds": [
    ],
    "layerOptions": 0,
    "shouldTrim": false
  },
  "frame": {
    "_class": "rect",
    "constrainProportions": false,
    "height": 48,
    "width": 1071,
    "x": 0,
    "y": 136
  },
  "hasClickThrough": false,
  "isFlippedHorizontal": false,
  "isFlippedVertical": false,
  "isLocked": false,
  "isVisible": true,
  "layerListExpandedType": 2,
  "layers": [
    {
      "class": "symbolInstance",
      "id": "314FD4F3-2C77-425E-974B-57EDDF593334"
    },
    {
      "class": "symbolInstance",
      "id": "3365F2E6-FFFE-406A-9E79-2EC6016EC8F9"
    },
    {
      "class": "symbolInstance",
      "id": "9F78B3F4-3059-469A-B82A-C19A0121C6DC"
    },
    {
      "class": "symbolInstance",
      "id": "A061F8A9-F4B9-469F-830D-4CD99DDA17F1"
    },
    {
      "class": "symbolInstance",
      "id": "AF560B86-22D5-4B84-8D06-D61DAD2343B3"
    }
  ],
  "name": "row",
  "nameIsFixed": true,
  "resizingConstraint": 63,
  "resizingType": 0,
  "rotation": 0,
  "shouldBreakMaskChain": false,
  "style": {
    "_class": "style",
    "endDecorationType": 0,
    "miterLimit": 10,
    "startDecorationType": 0
  },
  "userInfo": {
    "com.animaapp.stc-sketch-plugin": {
      "kModelPropertiesKey": {
      }
    }
  }
}