{
  "_class": "shapePath",
  "booleanOperation": -1,
  "do_objectID": "06B526ED-E34D-405E-8C60-EAD4BB2C1336",
  "edited": true,
  "exportOptions": {
    "_class": "exportOptions",
    "exportFormats": [
    ],
    "includedLayerIds": [
    ],
    "layerOptions": 0,
    "shouldTrim": false
  },
  "frame": {
    "_class": "rect",
    "constrainProportions": false,
    "height": 36.05715208295281,
    "width": 44,
    "x": 0,
    "y": 0
  },
  "isFlippedHorizontal": false,
  "isFlippedVertical": false,
  "isLocked": false,
  "isVisible": true,
  "layerListExpandedType": 0,
  "name": "Path",
  "nameIsFixed": false,
  "path": {
    "_class": "path",
    "isClosed": true,
    "pointRadiusBehaviour": 1,
    "points": [
      {
        "_class": "curvePoint",
        "cornerRadius": 0,
        "curveFrom": "{0.89994293323188135, 0.169683906773619}",
        "curveMode": 4,
        "curveTo": "{0.94997146661594289, 0.14647133402756934}",
        "hasCurveFrom": false,
        "hasCurveTo": true,
        "point": "{0.89994293323188135, 0.169683906773619}"
      },
      {
        "_class": "curvePoint",
        "cornerRadius": 0,
        "curveFrom": "{1, 0.14531070539026791}",
        "curveMode": 4,
        "curveTo": "{1, 0.14531070539026791}",
        "hasCurveFrom": true,
        "hasCurveTo": false,
        "point": "{1, 0.14531070539026791}"
      },
      {
        "_class": "curvePoint",
        "cornerRadius": 0,
        "curveFrom": "{0.89994293323188135, 0.26740883803448884}",
        "curveMode": 4,
        "curveTo": "{0.9159216283051177, 0.25998081475575441}",
        "hasCurveFrom": false,
        "hasCurveTo": true,
        "point": "{0.89994293323188135, 0.26740883803448884}"
      },
      {
        "_class": "curvePoint",
        "cornerRadius": 0,
        "curveFrom": "{0.89845419275646543, 0.29174818713713468}",
        "curveMode": 4,
        "curveTo": "{0.89994293323188135, 0.26740883803448884}",
        "hasCurveFrom": true,
        "hasCurveTo": false,
        "point": "{0.89994293323188135, 0.26740883803448884}"
      },
      {
        "_class": "curvePoint",
        "cornerRadius": 0,
        "curveFrom": "{0.7080083697926588, 1.3465613449983369}",
        "curveMode": 4,
        "curveTo": "{0.89845419275646543, 0.31618909308189885}",
        "hasCurveFrom": true,
        "hasCurveTo": true,
        "point": "{0.89994293323188135, 0.3405284421845447}"
      },
      {
        "_class": "curvePoint",
        "cornerRadius": 0,
        "curveFrom": "{0.25813201445691586, 0.90970072591768159}",
        "curveMode": 4,
        "curveTo": "{0, 0.90227270263894455}",
        "hasCurveFrom": true,
        "hasCurveTo": true,
        "point": "{0, 0.90227270263894455}"
      },
      {
        "_class": "curvePoint",
        "cornerRadius": 0,
        "curveFrom": "{0.12992200875023871, 0.75324798560930672}",
        "curveMode": 4,
        "curveTo": "{0.28000760890241666, 0.78017456999472357}",
        "hasCurveFrom": true,
        "hasCurveTo": true,
        "point": "{0.28000760890241666, 0.78017456999472357}"
      },
      {
        "_class": "curvePoint",
        "cornerRadius": 0,
        "curveFrom": "{0.12793831958858659, 0.65169678334975123}",
        "curveMode": 4,
        "curveTo": "{0.10005706676811865, 0.63370323596715161}",
        "hasCurveFrom": true,
        "hasCurveTo": true,
        "point": "{0.10005706676811865, 0.63370323596715161}"
      },
      {
        "_class": "curvePoint",
        "cornerRadius": 0,
        "curveFrom": "{0.018071143237591028, 0.55803024881502994}",
        "curveMode": 4,
        "curveTo": "{0.16244945256159768, 0.6411934372793695}",
        "hasCurveFrom": true,
        "hasCurveTo": true,
        "point": "{0.1801407646946957, 0.60933003458380053}"
      },
      {
        "_class": "curvePoint",
        "cornerRadius": 0,
        "curveFrom": "{0.06899923400532576, 0.39058138284944244}",
        "curveMode": 4,
        "curveTo": "{0.040136960243487348, 0.36513376929535868}",
        "hasCurveFrom": true,
        "hasCurveTo": true,
        "point": "{0.040136960243487348, 0.36513376929535868}"
      },
      {
        "_class": "curvePoint",
        "cornerRadius": 0,
        "curveFrom": "{0.12003043560966457, 0.38463233040204114}",
        "curveMode": 4,
        "curveTo": "{0.10272965857990836, 0.40656613214672782}",
        "hasCurveFrom": true,
        "hasCurveTo": true,
        "point": "{0.13810157884725344, 0.41155891478745799}"
      },
      {
        "_class": "curvePoint",
        "cornerRadius": 0,
        "curveFrom": "{0.060110329085031111, 0.047817899856861003}",
        "curveMode": 4,
        "curveTo": "{-0.031957390146470456, 0.16248800922234488}",
        "hasCurveFrom": true,
        "hasCurveTo": true,
        "point": "{0.060110329085031111, 0.047817899856861003}"
      },
      {
        "_class": "curvePoint",
        "cornerRadius": 0,
        "curveFrom": "{0.46623549552977239, 0.31383398352659075}",
        "curveMode": 4,
        "curveTo": "{0.17215141715807644, 0.29201416514530282}",
        "hasCurveFrom": false,
        "hasCurveTo": true,
        "point": "{0.46623549552977239, 0.31383398352659075}"
      },
      {
        "_class": "curvePoint",
        "cornerRadius": 0,
        "curveFrom": "{0.48281462097551775, 0.29140441164734071}",
        "curveMode": 4,
        "curveTo": "{0.48620886437131616, 0.30895934324991947}",
        "hasCurveFrom": true,
        "hasCurveTo": false,
        "point": "{0.48620886437131616, 0.30895934324991947}"
      },
      {
        "_class": "curvePoint",
        "cornerRadius": 0,
        "curveFrom": "{0.48221419060300869, 0.11431885095475339}",
        "curveMode": 4,
        "curveTo": "{0.48146977430632187, 0.27335235400302116}",
        "hasCurveFrom": true,
        "hasCurveTo": true,
        "point": "{0.48221419060300869, 0.25533830020654608}"
      },
      {
        "_class": "curvePoint",
        "cornerRadius": 0,
        "curveFrom": "{0.83146281148944656, 0}",
        "curveMode": 3,
        "curveTo": "{0.57589628593991682, 0}",
        "hasCurveFrom": true,
        "hasCurveTo": true,
        "point": "{0.69145900703823815, 0}"
      },
      {
        "_class": "curvePoint",
        "cornerRadius": 0,
        "curveFrom": "{0.86151797603196212, 0.097724931260869841}",
        "curveMode": 4,
        "curveTo": "{0.86151797603196212, 0.097724931260869841}",
        "hasCurveFrom": false,
        "hasCurveTo": true,
        "point": "{0.86151797603196212, 0.097724931260869841}"
      },
      {
        "_class": "curvePoint",
        "cornerRadius": 0,
        "curveFrom": "{0.96005326231691246, 0.023444698473507292}",
        "curveMode": 4,
        "curveTo": "{0.96157504280008066, 0.024605327110813997}",
        "hasCurveFrom": true,
        "hasCurveTo": false,
        "point": "{0.96157504280008066, 0.024605327110813997}"
      }
    ]
  },
  "resizingConstraint": 63,
  "resizingType": 0,
  "rotation": 0,
  "shouldBreakMaskChain": false
}