{
  "_class": "shapeGroup",
  "clippingMaskMode": 0,
  "do_objectID": "4538B308-DB4D-4AE1-94B0-04D2280BF2D8",
  "exportOptions": {
    "_class": "exportOptions",
    "exportFormats": [
    ],
    "includedLayerIds": [
    ],
    "layerOptions": 0,
    "shouldTrim": false
  },
  "frame": {
    "_class": "rect",
    "constrainProportions": true,
    "height": 28,
    "width": 28,
    "x": 0,
    "y": 0
  },
  "hasClickThrough": false,
  "hasClippingMask": false,
  "isFlippedHorizontal": false,
  "isFlippedVertical": false,
  "isLocked": false,
  "isVisible": true,
  "layerListExpandedType": 1,
  "layers": [
    {
      "class": "oval",
      "id": "E5F6DD14-74CB-4639-8F04-7BC417866C3F"
    }
  ],
  "name": "Dot",
  "nameIsFixed": true,
  "originalObjectID": "878C0D06-1681-414D-A1C0-FDD41BDA8928",
  "resizingConstraint": 63,
  "resizingType": 0,
  "rotation": 0,
  "shouldBreakMaskChain": false,
  "style": {
    "_class": "style",
    "blur": {
      "_class": "blur",
      "center": "{0.5, 0.5}",
      "isEnabled": false,
      "motionAngle": 0,
      "radius": 5,
      "type": 0
    },
    "borders": [
      {
        "_class": "border",
        "color": {
          "_class": "color",
          "alpha": 1,
          "blue": 0.7810374149659864,
          "green": 0.7810374149659864,
          "red": 0.7810374149659864
        },
        "fillType": 0,
        "isEnabled": true,
        "position": 0,
        "thickness": 7.5
      }
    ],
    "endDecorationType": 0,
    "fills": [
      {
        "_class": "fill",
        "color": {
          "_class": "color",
          "alpha": 1,
          "blue": 0.9764705882352941,
          "green": 0.9764705882352941,
          "red": 0.9764705882352941
        },
        "fillType": 0,
        "isEnabled": true,
        "noiseIndex": 0,
        "noiseIntensity": 0,
        "patternFillType": 0,
        "patternTileScale": 1
      }
    ],
    "miterLimit": 10,
    "startDecorationType": 0
  },
  "windingRule": 1
}