{
  "_class": "shapeGroup",
  "clippingMaskMode": 0,
  "do_objectID": "7393940E-739A-4FA7-8304-622DB78010B9",
  "exportOptions": {
    "_class": "exportOptions",
    "do_objectID": "82E5BC44-8107-475E-A3EE-321FDCD1D8FB",
    "exportFormats": [
    ],
    "includedLayerIds": [
    ],
    "layerOptions": 0,
    "shouldTrim": false
  },
  "frame": {
    "_class": "rect",
    "constrainProportions": false,
    "do_objectID": "6309E459-B75E-48C2-BED0-E7C22D8B218B",
    "height": 63,
    "width": 139,
    "x": 0,
    "y": 4
  },
  "hasClickThrough": false,
  "hasClippingMask": false,
  "isFlippedHorizontal": false,
  "isFlippedVertical": false,
  "isLocked": false,
  "isVisible": true,
  "layerListExpandedType": 0,
  "layers": [
    {
      "class": "rectangle",
      "id": "70375DB0-2EB5-4375-92F7-5102C6E1B492"
    }
  ],
  "name": "label-box",
  "nameIsFixed": false,
  "resizingConstraint": 63,
  "resizingType": 0,
  "rotation": 0,
  "shouldBreakMaskChain": false,
  "style": {
    "_class": "style",
    "do_objectID": "4FFCA39A-8385-4418-B410-92D1F7330AAB",
    "endDecorationType": 0,
    "fills": [
      {
        "_class": "fill",
        "color": {
          "_class": "color",
          "alpha": 1,
          "blue": 0.137255,
          "green": 0.65098,
          "red": 0.960784
        },
        "fillType": 0,
        "isEnabled": true,
        "noiseIndex": 0,
        "noiseIntensity": 0,
        "patternFillType": 1,
        "patternTileScale": 1
      }
    ],
    "miterLimit": 10,
    "sharedObjectID": "338603F0-EF32-4117-98DB-75EE20EDD183",
    "startDecorationType": 0
  },
  "userInfo": {
    "com.animaapp.stc-sketch-plugin": {
      "kModelPropertiesKey": {
      }
    }
  },
  "windingRule": 1
}