{
  "_class": "group",
  "do_objectID": "AD0E4C7F-D216-4AB0-90BF-D04837FC349C",
  "exportOptions": {
    "_class": "exportOptions",
    "exportFormats": [
    ],
    "includedLayerIds": [
    ],
    "layerOptions": 0,
    "shouldTrim": false
  },
  "frame": {
    "_class": "rect",
    "constrainProportions": false,
    "height": 366,
    "width": 280,
    "x": 580,
    "y": 329
  },
  "hasClickThrough": false,
  "isFlippedHorizontal": false,
  "isFlippedVertical": false,
  "isLocked": false,
  "isVisible": true,
  "layerListExpandedType": 2,
  "layers": [
    {
      "class": "shapeGroup",
      "id": "6351A96E-B548-4BBA-9962-6EA44EAC1579"
    },
    {
      "class": "group",
      "id": "E7B0C179-23AD-4673-965C-AA837AC59DA1"
    },
    {
      "class": "group",
      "id": "988A6C3F-E0D6-4766-8950-01F114914571"
    },
    {
      "class": "text",
      "id": "1EE9388C-582D-48CF-A7B4-145AEB42AD28"
    }
  ],
  "name": "Modal",
  "nameIsFixed": true,
  "resizingConstraint": 63,
  "resizingType": 0,
  "rotation": 0,
  "shouldBreakMaskChain": false,
  "style": {
    "_class": "style",
    "endDecorationType": 0,
    "miterLimit": 10,
    "startDecorationType": 0
  },
  "userInfo": {
    "com.animaapp.stc-sketch-plugin": {
      "kModelPropertiesKey": {
      }
    }
  }
}